LICENSE.txt
README.md
setup.py
async_proxy/__init__.py
async_proxy/connector.py
async_proxy/errors.py
async_proxy/helpers.py
async_proxy/proto.py
async_proxy.egg-info/PKG-INFO
async_proxy.egg-info/SOURCES.txt
async_proxy.egg-info/dependency_links.txt
async_proxy.egg-info/requires.txt
async_proxy.egg-info/top_level.txt