Metadata-Version: 2.1
Name: async-proxy
Version: 1.2.0
Summary: Full-featured proxy connector for aiohttp
Home-page: https://github.com/Skactor/aiohttp-proxy
Author: Joongi Kim
Author-email: me@daybreaker.info
License: apache2
Classifier: Programming Language :: Python :: 3.8
Classifier: Programming Language :: Python :: 3.9
Classifier: Programming Language :: Python :: 3.10
Classifier: License :: OSI Approved :: Apache Software License
Requires-Python: >=3.7, <=3.10
License-File: LICENSE.txt
